migrations/__init__.py
request_watch-0.1.dist-info/METADATA
request_watch-0.1.dist-info/WHEEL
request_watch-0.1.dist-info/top_level.txt
request_watch-0.1.dist-info/RECORD
