Metadata-Version: 2.1
Name: request-watch
Version: 0.1
Requires-Dist: Django (>=2.2)
